LICENSE
README.md
setup.py
clipboard_many_files/__init__.py
clipboard_many_files/main.py
clipboard_many_files/x11.py
clipboard_many_files.egg-info/PKG-INFO
clipboard_many_files.egg-info/SOURCES.txt
clipboard_many_files.egg-info/dependency_links.txt
clipboard_many_files.egg-info/entry_points.txt
clipboard_many_files.egg-info/top_level.txt