Metadata-Version: 2.2
Name: clipboard-many-files
Version: 1.0.3
Summary: Place several files on clipboard from the command-line
Home-page: https://github.com/talwrii/clipboard-many-files
Author: @readwithai
Author-email: talwrii@gmail.com
License: MIT
Keywords: clipboard,files
License-File: LICENSE
Dynamic: author
Dynamic: author-email
Dynamic: description
Dynamic: description-content-type
Dynamic: home-page
Dynamic: keywords
Dynamic: license
Dynamic: summary
